twitter_nlp_toolkit/__init__.py
twitter_nlp_toolkit/twitter-nlp-toolkit.py
twitter_nlp_toolkit/file_fetcher/__init__.py
twitter_nlp_toolkit/file_fetcher/file_fetcher.py
twitter_nlp_toolkit/tweet_json_parser/__init__.py
twitter_nlp_toolkit/tweet_json_parser/tweet_json_parser.py
twitter_nlp_toolkit/tweet_sentiment_classifier/__init__.py
twitter_nlp_toolkit/tweet_sentiment_classifier/tweet_sentiment_classifier.py
twitter_nlp_toolkit/tweet_sentiment_classifier/models/__init__.py
twitter_nlp_toolkit/tweet_sentiment_classifier/models/bert_models.py
twitter_nlp_toolkit/tweet_sentiment_classifier/models/bow_models.py
twitter_nlp_toolkit/tweet_sentiment_classifier/models/lstm_models.py
twitter_nlp_toolkit/twitter_REST_downloader/__init__.py
twitter_nlp_toolkit/twitter_REST_downloader/twitter_REST_downloader.py
twitter_nlp_toolkit/twitter_listener/__init__.py
twitter_nlp_toolkit/twitter_listener/twitter_listener.py
twitter_nlp_toolkit-0.1.8.dist-info/LICENSE.txt
twitter_nlp_toolkit-0.1.8.dist-info/METADATA
twitter_nlp_toolkit-0.1.8.dist-info/WHEEL
twitter_nlp_toolkit-0.1.8.dist-info/top_level.txt
twitter_nlp_toolkit-0.1.8.dist-info/RECORD
