Metadata-Version: 2.1
Name: twitter-nlp-toolkit
Version: 0.1.8
Summary: Tools for collecting , processing and analyzing twitter data
Home-page: https://github.com/eschibli/twitter-toolbox
Author: Eric Schibli , Mohamad (Moe) Antar
Author-email: moe.antar14@gmail.com
License: UNKNOWN
Keywords: twitter sentiment analysis
Platform: UNKNOWN
Classifier: Programming Language :: Python :: 3.6
Classifier: Operating System :: OS Independent
Requires-Python: >=3.6
Requires-Dist: scikit-learn (>=0.22)
Requires-Dist: tensorflow (>=2)
Requires-Dist: pandas
Requires-Dist: numpy
Requires-Dist: ftfy
Requires-Dist: tweepy
Requires-Dist: tqdm
Requires-Dist: requests
Requires-Dist: spacy
Requires-Dist: bert-for-tf2
Requires-Dist: tensorflow-hub
